agenticontrol/__init__.py
agenticontrol/client.py
agenticontrol/exceptions.py
agenticontrol/models.py
agenticontrol/risk_engine.py
agenticontrol/hooks/__init__.py
agenticontrol/hooks/langchain_handler.py
agenticontrol/local/__init__.py
agenticontrol/local/viewer.py
agenticontrol-0.1.0.dist-info/METADATA
agenticontrol-0.1.0.dist-info/WHEEL
agenticontrol-0.1.0.dist-info/top_level.txt
agenticontrol-0.1.0.dist-info/RECORD
