Metadata-Version: 2.4
Name: agenticontrol
Version: 0.1.0
Summary: AGENTICONTROL V0 MVP - Control plane for AI agents with synchronous blocking and asynchronous logging
Author: AGENTICONTROL Team
License-Expression: MIT
Project-URL: Homepage, https://github.com/agenticontrol/agenticontrol
Project-URL: Documentation, https://github.com/agenticontrol/agenticontrol#readme
Project-URL: Repository, https://github.com/agenticontrol/agenticontrol
Project-URL: Issues, https://github.com/agenticontrol/agenticontrol/issues
Keywords: ai,agents,langchain,monitoring,control-plane,observability
Classifier: Development Status :: 3 - Alpha
Classifier: Intended Audience :: Developers
Classifier: Programming Language :: Python :: 3
Classifier: Programming Language :: Python :: 3.10
Classifier: Programming Language :: Python :: 3.11
Classifier: Programming Language :: Python :: 3.12
Classifier: Topic :: Software Development :: Libraries :: Python Modules
Classifier: Topic :: Scientific/Engineering :: Artificial Intelligence
Requires-Python: >=3.10
Requires-Dist: pydantic>=2.0.0
Requires-Dist: langchain>=0.1.0
Requires-Dist: aiohttp>=3.9.0
Requires-Dist: rich>=13.0.0
Provides-Extra: dev
Requires-Dist: pytest>=7.4.0; extra == "dev"
Requires-Dist: pytest-asyncio>=0.21.0; extra == "dev"
Requires-Dist: pytest-mock>=3.11.0; extra == "dev"
Requires-Dist: black>=23.0.0; extra == "dev"
Requires-Dist: ruff>=0.1.0; extra == "dev"
Requires-Dist: mypy>=1.5.0; extra == "dev"
Requires-Dist: types-aiofiles>=23.0.0; extra == "dev"
